parasut_cli/__init__.py
parasut_cli/cli.py
parasut_cli/commands/__init__.py
parasut_cli/commands/link.py
parasut_cli/commands/release.py
parasut_cli/commands/run.py
parasut_cli/commands/start.py
parasut_cli/commands/switch.py
parasut_cli/commands/version.py
parasut_cli/config/__init__.py
parasut_cli/config/settings.py
parasut_cli/state/.gitkeep
parasut_cli/state/link_info.pickle
parasut_cli/utils/__init__.py
parasut_cli/utils/command.py
parasut_cli/utils/invoker.py
parasut_cli/utils/receiver.py
parasut_cli-0.6.3.dist-info/AUTHORS.rst
parasut_cli-0.6.3.dist-info/LICENSE
parasut_cli-0.6.3.dist-info/METADATA
parasut_cli-0.6.3.dist-info/WHEEL
parasut_cli-0.6.3.dist-info/entry_points.txt
parasut_cli-0.6.3.dist-info/top_level.txt
parasut_cli-0.6.3.dist-info/RECORD
