Metadata-Version: 2.1
Name: parasut-cli
Version: 0.6.3
Summary: CLI for Parasut workspace management
Home-page: https://github.com/mthnglac/parasut-cli
Author: Metehan Gulac
Author-email: metehanglc@protonmail.com
License: MIT license
Keywords: parasut-cli
Platform: UNKNOWN
Classifier: Development Status :: 2 - Pre-Alpha
Classifier: Intended Audience :: Developers
Classifier: License :: OSI Approved :: MIT License
Classifier: Natural Language :: English
Classifier: Programming Language :: Python :: 3
Classifier: Programming Language :: Python :: 3.6
Classifier: Programming Language :: Python :: 3.7
Classifier: Programming Language :: Python :: 3.8
Classifier: Programming Language :: Python :: 3.9
Requires-Python: >=3.6
Requires-Dist: python-dotenv
Requires-Dist: libtmux
Requires-Dist: pygit2
Requires-Dist: rich
